pigit/__init__.py
pigit/__main__.py
pigit/app.py
pigit/config.py
pigit/console_scripts.py
pigit/const.py
pigit/entry.py
pigit/info.py
pigit/shellmode.py
pigit/cmdparse/__init__.py
pigit/cmdparse/parser.py
pigit/cmdparse/completion/__init__.py
pigit/cmdparse/completion/base.py
pigit/cmdparse/completion/bash.py
pigit/cmdparse/completion/fish.py
pigit/cmdparse/completion/zsh.py
pigit/ext/__init__.py
pigit/ext/executor.py
pigit/ext/func.py
pigit/ext/lcstat.py
pigit/ext/log.py
pigit/ext/singleton.py
pigit/ext/utils.py
pigit/git/__init__.py
pigit/git/_cmd_func.py
pigit/git/_cmds.py
pigit/git/model.py
pigit/git/proxy.py
pigit/git/repo.py
pigit/git/ignore/__init__.py
pigit/git/ignore/template.py
pigit/tui/__init__.py
pigit/tui/components.py
pigit/tui/console.py
pigit/tui/event_loop.py
pigit/tui/input.py
pigit/tui/utils.py
tests/__init__.py
tests/conftest.py
tests/test_all_pigit.py
tests/test_cmdparse.py
tests/test_config.py
tests/test_ext.py
tests/test_ext_executor.py
tests/test_ext_lcstat.py
tests/test_git.py
tests/test_git_cmd.py
tests/test_git_ignore.py
tests/test_info.py
tests/test_shell.py
tests/test_tui_components.py
tests/test_tui_console.py
tests/test_tui_eventloop.py
tests/test_tui_input.py
tests/utils.py
pigit-1.7.0.dist-info/LICENSE
pigit-1.7.0.dist-info/METADATA
pigit-1.7.0.dist-info/WHEEL
pigit-1.7.0.dist-info/entry_points.txt
pigit-1.7.0.dist-info/top_level.txt
pigit-1.7.0.dist-info/RECORD
